nonin/__init__.py
nonin/__main__.py
nonin/device.py
nonin/outlet.py
nonin-0.2.4.dist-info/METADATA
nonin-0.2.4.dist-info/WHEEL
nonin-0.2.4.dist-info/entry_points.txt
nonin-0.2.4.dist-info/top_level.txt
nonin-0.2.4.dist-info/RECORD
